blinkparse/__init__.py
blinkparse/argument.py
blinkparse/arguments.py
blinkparse/command.py
blinkparse/commandArgument.py
blinkparse/parser.py
blinkparse-0.1.5.dist-info/LICENSE
blinkparse-0.1.5.dist-info/METADATA
blinkparse-0.1.5.dist-info/WHEEL
blinkparse-0.1.5.dist-info/top_level.txt
blinkparse-0.1.5.dist-info/RECORD
